Workbook

Sheet Inputs & References
L24: 46.452
L25: 16.473
L26: =L24-L25 -> 29.979

Sheet SOTP Valuation
B1: Discount Period | D1: 1 | E1: 2 | F1: 3 | G1: 4 | H1: 5
C2: Base Year 2025 | D2: 2026 | E2: 2027 | F2: 2028 | G2: 2029 | H2: 2030 | R2: Componente | S2: Value 2026 (EUR bn)
B3: Automotive | R3: Automotive | S3: =D15*D30 -> 19.4097
B4: Revenue Automotive | C4: 280 | D4: 275 | E4: =D4*1.02 -> 280.5 | F4: =E4*1.02 -> 286.11 | G4: =F4*1.01 -> 288.9711 | H4: =G4*1.01 -> 291.86081 | R4: China Business | S4: =D22 -> 3
B5: EBITDA Ratio | C5: 0.14 | D5: 0.14 | E5: 0.145 | F5: 0.15 | G5: 0.15 | H5: 0.155 | R5: Finance Business | S5: =D29 -> 11.5875
B6: EBITDA | C6: =C4*C5 -> 39.2 | D6: =D4*D5 -> 38.5 | E6: =E4*E5 -> 40.6725 | F6: =F4*F5 -> 42.9165 | G6: =G4*G5 -> 43.345665 | H6: =H4*H5 -> 45.238426
B7: EBIT Ratio | C7: 0.028 | D7: 0.02 | E7: 0.045 | F7: 0.05 | G7: 0.055 | H7: 0.06
B8: EBIT | C8: 5.279 | D8: =D4*D7 -> 5.5 | E8: =E4*E7 -> 12.6225 | F8: =F4*F7 -> 14.3055 | G8: =G4*G7 -> 15.893411 | H8: =H4*H7 -> 17.511649
B9: (1−T) | C9: 0.72 | D9: =$C$9 -> 0.72 | E9: =$C$9 -> 0.72 | F9: =$C$9 -> 0.72 | G9: =$C$9 -> 0.72 | H9: =$C$9 -> 0.72
B10: BAI (Earnings after tax) | C10: 9.307 | D10: 9.567 | E10: 14.131 | F10: 18.198 | G10: 18.729 | H10: 28.7
B11: BAN (Earnings before tax) | C11: 7.323 | D11: 6.462 | E11: 9.545 | F11: 12.292 | G11: 12.651 | H11: 12.976
B12: D&A | C12: 30 | D12: 29.979 | E12: 28.04 | F12: 27.603 | G12: 27.118 | H12: 27.118
B13: Δ NWC Automotive (€bn) | C13: 2.744 | D13: 1.5 | E13: 0.1 | F13: 0.1 | G13: 0.1 | H13: 0.1
B14: CapEx (€bn) +Capitalzed development costs | C14: 23.999 | D14: 24 | E14: 27 | F14: 28 | G14: 29.983 | H14: 30
B15: FCF | C15: =C8*C9+C12-C13-C14 -> 7.05788 | D15: =D8*D9+D12-D13-D14 -> 8.439 | E15: =E8*E9+E12-E13-E14 -> 10.0282 | F15: =F8*F9+F12-F13-F14 -> 9.80296 | G15: =G8*G9+G12-G13-G14 -> 8.4782556 | H15: =H8*H9+H12-H13-H14 -> 9.626387
B17: Discount Period | D17: 1 | E17: 2 | F17: 3 | G17: 4 | H17: 5
C18: Base Year 2025 | D18: 2026 | E18: 2027 | F18: 2028 | G18: 2029 | H18: 2030
B19: China Business
B20: NetIncome | C20: 0.944 | D20: 0.6 | E20: =D20*1.03 -> 0.618 | F20: =E20*1.03 -> 0.63654 | G20: =F20*1.03 -> 0.6556362 | H20: =G20*1.03 -> 0.67530529
B21: P/E | C21: 8 | D21: 5 | E21: =D21*1.1 -> 5.5 | F21: =E21*1.1 -> 6.05 | G21: =F21*1.1 -> 6.655 | H21: =G21*1.1 -> 7.3205
B22: Value China | C22: =C21*C20 -> 7.552 | D22: =D20*D21 -> 3 | E22: =E20*E21 -> 3.399 | F22: =F20*F21 -> 3.851067 | G22: =G20*G21 -> 4.3632589 | H22: =H20*H21 -> 4.9435723
B24: Discount Period | D24: 1 | E24: 2 | F24: 3 | G24: 4 | H24: 5
C25: Base Year 2025 | D25: 2026 | E25: 2027 | F25: 2028 | G25: 2029 | H25: 2030
B26: Finace Business
B27: BookValueFS​≈ | C27: 45 | D27: =C27*1.03 -> 46.35 | E27: =D27*1.03 -> 47.7405 | F27: =E27*1.03 -> 49.172715 | G27: =F27*1.03 -> 50.647896 | H27: =G27*1.03 -> 52.167333
B28: Ratio P/B | C28: 0.25 | D28: =$C$28 -> 0.25 | E28: =$C$28 -> 0.25 | F28: =$C$28 -> 0.25 | G28: =$C$28 -> 0.25 | H28: =$C$28 -> 0.25
B29: Value Finance | C29: =C28*C27 -> 11.25 | D29: =D27*D28 -> 11.5875 | E29: =E27*E28 -> 11.935125 | F29: =F27*F28 -> 12.293179 | G29: =G27*G28 -> 12.661974 | H29: =H27*H28 -> 13.041833
B30: Automotive FCF multiple | C30: 2.3 | D30: 2.3 | E30: 2.3 | F30: 2.3 | G30: 2.3 | H30: 2.3
B32: SOTP equity value (EUR bn) | C32: =C15*C30+C22+C29 -> 35.035124 | D32: =D15*D30+D22+D29 -> 33.9972 | E32: =E15*E30+E22+E29 -> 38.398985 | F32: =F15*F30+F22+F29 -> 38.691054 | G32: =G15*G30+G22+G29 -> 36.525221 | H32: =H15*H30+H22+H29 -> 40.126096
B33: Shares outstanding (bn) | C33: 0.501 | D33: 0.501 | E33: 0.501 | F33: 0.501 | G33: 0.501 | H33: 0.501
B34: Implied value / share (EUR) | C34: =IFERROR(C32/C33,"") -> 69.930387 | D34: =IFERROR(D32/D33,"") -> 67.858683 | E34: =IFERROR(E32/E33,"") -> 76.644681 | F34: =IFERROR(F32/F33,"") -> 77.227652 | G34: =IFERROR(G32/G33,"") -> 72.904632 | H34: =IFERROR(H32/H33,"") -> 80.092008
E37: 29.979 28.040 27.603 27.118 28.199

Sheet DCF by Business
B2: Scenario Base | E2: Discount Period | G2: 1 | H2: 2 | I2: 3 | J2: 4 | K2: 5
F3: Base Year | G3: 2026 | H3: 2027 | I3: 2028 | J3: 2029 | K3: 2030
B4: WACC | C4: 0.09 | E4: FCF (B€) Automotive | F4: 4 | G4: 4.08 | H4: 4.16 | I4: 4.25 | J4: 4.33 | K4: 4.42 | N4: Automotive | O4: =G8 -> 51
B5: Growth | C5: 0.01 | E5: PV (FCF) Automotive | F5: - | G5: =G4/(1+$C$4)^G2 -> 3.7431193 | H5: =H4/(1+$C$4)^H2 -> 3.5013888 | I5: =I4/(1+$C$4)^I2 -> 3.2817798 | J5: =J4/(1+$C$4)^J2 -> 3.0674812 | K5: =K4/(1+$C$4)^K2 -> 2.8726967 | N5: Financial Services | O5: =G9 -> 11.5875
B6: Number of Stocks (Billions) | C6: 0.501 | E6: Sum of PV FCF (FY25-29) Automotive | G6: =SUM($G$5:G5) -> 3.7431193 | H6: =SUM($G$5:H5) -> 7.244508 | I6: =SUM($G$5:I5) -> 10.526288 | J6: =SUM($G$5:J5) -> 13.593769 | K6: =SUM($G$5:K5) -> 16.466466 | N6: China JV | O6: =G10 -> 3
E7: Terminal Value (TV) Automotive | F7: - | G7: =(G4*(1+$C$5)/($C$4-$C$5))/(1+$C$4)^G2 -> 47.256881 | H7: =(H4*(1+$C$5)/($C$4-$C$5))/(1+$C$4)^H2 -> 44.205033 | I7: =(I4*(1+$C$5)/($C$4-$C$5))/(1+$C$4)^I2 -> 41.43247 | J7: =(J4*(1+$C$5)/($C$4-$C$5))/(1+$C$4)^J2 -> 38.72695 | K7: =(K4*(1+$C$5)/($C$4-$C$5))/(1+$C$4)^K2 -> 36.267796
E8: Enterprise Value (EV) Automotive | F8: - | G8: =G6+G7 -> 51 | H8: =H6+H7 -> 51.449541 | I8: =I6+I7 -> 51.958758 | J8: =J6+J7 -> 52.320719 | K8: =K6+K7 -> 52.734262 | O8: =SUM(O4:O6) -> 65.5875
E9: Financial Services (Book Value) | F9: ='SOTP Valuation'!C29 -> 11.25 | G9: ='SOTP Valuation'!D29 -> 11.5875 | H9: ='SOTP Valuation'!E29 -> 11.935125 | I9: ='SOTP Valuation'!F29 -> 12.293179 | J9: ='SOTP Valuation'!G29 -> 12.661974 | K9: ='SOTP Valuation'!H29 -> 13.041833
E10: China Joint Ventures | F10: ='SOTP Valuation'!C22 -> 7.552 | G10: ='SOTP Valuation'!D22 -> 3 | H10: ='SOTP Valuation'!E22 -> 3.399 | I10: ='SOTP Valuation'!F22 -> 3.851067 | J10: ='SOTP Valuation'!G22 -> 4.3632589 | K10: ='SOTP Valuation'!H22 -> 4.9435723
E11: Debt /PV Debt | F11: -34.5 | G11: =$F$11/(1+$C$4)^G$2 -> -31.651376 | H11: =$F$11/(1+$C$4)^H$2 -> -29.03796 | I11: =$F$11/(1+$C$4)^I$2 -> -26.64033 | J11: =$F$11/(1+$C$4)^J$2 -> -24.44067 | K11: =$F$11/(1+$C$4)^K$2 -> -22.422633
E12: Equtity Value | G12: =G8+G11+G9+G10 -> 33.936124 | H12: =H8+H11+H9+H10 -> 37.745707 | I12: =I8+I11+I9+I10 -> 41.462673 | J12: =J8+J11+J9+J10 -> 44.905282 | K12: =K8+K11+K9+K10 -> 48.297035
E13: Stock Price | G13: =G12/$C$6 -> 67.736774 | H13: =H12/$C$6 -> 75.340732 | I13: =I12/$C$6 -> 82.759827 | J13: =J12/$C$6 -> 89.631301 | K13: =K12/$C$6 -> 96.401267

Sheet DCF Scenarios
B2: Scenario Bear | E2: Discount Period | G2: 1 | H2: 2 | I2: 3 | J2: 4 | K2: 5
F3: Base Year | G3: 2026 | H3: 2027 | I3: 2028 | J3: 2029 | K3: 2030
B4: WACC | C4: 0.105 | E4: EBIT (B€) | G4: 13.1 | H4: 12 | I4: 17.1 | J4: 19.2 | K4: 21.4
B5: Growth | C5: 0 | E5: FCF (B€) | F5: 5.8 | G5: 5.9 | H5: 5.93 | I5: 5.96 | J5: 5.99 | K5: 6.02
B6: Number of Stocks (Billions) | C6: 0.501 | E6: PV (FCF) | F6: - | G6: =G5/(1+$C$4)^G2 -> 5.3393665 | H6: =H5/(1+$C$4)^H2 -> 4.8565754 | I6: =I5/(1+$C$4)^I2 -> 4.4173257 | J6: =J5/(1+$C$4)^J2 -> 4.0177019 | K6: =K5/(1+$C$4)^K2 -> 3.6541393
E7: Sum of PV FCF (FY25-29) | G7: =SUM($G$6:G6) -> 5.3393665 | H7: =SUM($G$6:H6) -> 10.195942 | I7: =SUM($G$6:I6) -> 14.613268 | J7: =SUM($G$6:J6) -> 18.63097 | K7: =SUM($G$6:K6) -> 22.285109
E8: Terminal Value (TV) | F8: - | G8: =(G5*(1+$C$5)/($C$4-$C$5))/(1+$C$4)^G2 -> 50.85111 | H8: =(H5*(1+$C$5)/($C$4-$C$5))/(1+$C$4)^H2 -> 46.253099 | I8: =(I5*(1+$C$5)/($C$4-$C$5))/(1+$C$4)^I2 -> 42.069769 | J8: =(J5*(1+$C$5)/($C$4-$C$5))/(1+$C$4)^J2 -> 38.263828 | K8: =(K5*(1+$C$5)/($C$4-$C$5))/(1+$C$4)^K2 -> 34.801327
E9: Enterprise Value (EV) | F9: - | G9: =G7+G8 -> 56.190476 | H9: =H7+H8 -> 56.449041 | I9: =I7+I8 -> 56.683037 | J9: =J7+J8 -> 56.894797 | K9: =K7+K8 -> 57.086436
E10: Debt /PV Debt | F10: -34.5 | G10: =$F$10/(1+$C$4)^G2 -> -31.221719 | H10: =$F$10/(1+$C$4)^H2 -> -28.25495 | I10: =$F$10/(1+$C$4)^I2 -> -25.57009 | J10: =$F$10/(1+$C$4)^J2 -> -23.140353 | K10: =$F$10/(1+$C$4)^K2 -> -20.941496
E11: Equtity Value | G11: =G9+G10 -> 24.968757 | H11: =H9+H10 -> 28.194091 | I11: =I9+I10 -> 31.112946 | J11: =J9+J10 -> 33.754444 | K11: =K9+K10 -> 36.14494
E12: Stock Price | G12: =G11/$C$6 -> 49.837838 | H12: =H11/$C$6 -> 56.275632 | I12: =I11/$C$6 -> 62.101689 | J12: =J11/$C$6 -> 67.37414 | K12: =K11/$C$6 -> 72.145588
B15: Scenario Base | E15: Discount Period | G15: 1 | H15: 2 | I15: 3 | J15: 4 | K15: 5
F16: Base Year | G16: 2026 | H16: 2027 | I16: 2028 | J16: 2029 | K16: 2030
B17: WACC | C17: 0.09
B18: Growth | C18: 0.01 | E18: FCF (B€) | F18: 5.1 | G18: 5.2 | H18: 5.3 | I18: 5.41 | J18: 5.52 | K18: 5.63
B19: Number of Stocks (Billions) | C19: 0.501 | E19: PV (FCF) | F19: - | G19: =G18/(1+$C$17)^G15 -> 4.7706422 | H19: =H18/(1+$C$17)^H15 -> 4.460904 | I19: =I18/(1+$C$17)^I15 -> 4.1775126 | J19: =J18/(1+$C$17)^J15 -> 3.9105072 | K19: =K18/(1+$C$17)^K15 -> 3.6591137
E20: Sum of PV FCF (FY25-29) | G20: =SUM($G$19:G19) -> 4.7706422 | H20: =SUM($G$19:H19) -> 9.2315462 | I20: =SUM($G$19:I19) -> 13.409059 | J20: =SUM($G$19:J19) -> 17.319566 | K20: =SUM($G$19:K19) -> 20.97868
E21: Terminal Value (TV) | F21: - | G21: =(G18*(1+$C$18)/($C$17-$C$18))/((1+$C$17)^G15) -> 60.229358 | H21: =(H18*(1+$C$18)/($C$17-$C$18))/(1+$C$17)^H15 -> 56.318913 | I21: =(I18*(1+$C$18)/($C$17-$C$18))/(1+$C$17)^I15 -> 52.741097 | J21: =(J18*(1+$C$18)/($C$17-$C$18))/(1+$C$17)^J15 -> 49.370153 | K21: =((K18*(1+$C$18))/($C$17-$C$18))/(1+$C$17)^K15 -> 46.196311
E22: Enterprise Value (EV) | F22: - | G22: =G20+G21 -> 65 | H22: =H20+H21 -> 65.550459 | I22: =I20+I21 -> 66.150156 | J22: =J20+J21 -> 66.689719 | K22: =K20+K21 -> 67.17499
E23: Debt /PV Debt | F23: -34.5 | G23: =$F$23/(1+$C$17)^G15 -> -31.651376 | H23: =$F$23/(1+$C$17)^H15 -> -29.03796 | I23: =$F$23/(1+$C$17)^I15 -> -26.64033 | J23: =$F$23/(1+$C$17)^J15 -> -24.44067 | K23: =$F$23/(1+$C$17)^K15 -> -22.422633
E24: Equtity Value | G24: =G22+G23 -> 33.348624 | H24: =H22+H23 -> 36.512499 | I24: =I22+I23 -> 39.509826 | J24: =J22+J23 -> 42.249049 | K24: =K22+K23 -> 44.752357
E25: Stock Price | G25: =G24/$C$19 -> 66.564119 | H25: =H24/$C$19 -> 72.879239 | I25: =I24/$C$19 -> 78.861927 | J25: =J24/$C$19 -> 84.329439 | K25: =K24/$C$19 -> 89.326063
B28: Scenario Bull | E28: Discount Period | G28: 1 | H28: 2 | I28: 3 | J28: 4 | K28: 5
F29: Base Year | G29: 2026 | H29: 2027 | I29: 2028 | J29: 2029 | K29: 2030
B30: WACC | C30: 0.085
B31: Growth | C31: 0.015 | E31: FCF (B€) | F31: 5.4 | G31: 5.6 | H31: 5.77 | I31: 5.94 | J31: 6.12 | K31: 6.3
B32: Number of Stocks (Billions) | C32: 0.501 | E32: PV (FCF) | F32: - | G32: =G31/(1+$C$30)^G28 -> 5.1612903 | H32: =H31/(1+$C$30)^H28 -> 4.901357 | I32: =I31/(1+$C$30)^I28 -> 4.6504741 | J32: =J31/(1+$C$30)^J28 -> 4.4160346 | K32: =K31/(1+$C$30)^K28 -> 4.1897862
E33: Sum of PV FCF (FY25-29) | G33: =SUM($G$32:G32) -> 5.1612903 | H33: =SUM($G$32:H32) -> 10.062647 | I33: =SUM($G$32:I32) -> 14.713121 | J33: =SUM($G$32:J32) -> 19.129156 | K33: =SUM($G$32:K32) -> 23.318942
E34: Terminal Value (TV) | F34: - | G34: =(G31*(1+$C$31)/($C$30-$C$31))/((1+$C$30)^G28) -> 74.83871 | H34: =(H31*(1+$C$31)/($C$30-$C$31))/((1+$C$30)^H28) -> 71.069677 | I34: =(I31*(1+$C$31)/($C$30-$C$31))/((1+$C$30)^I28) -> 67.431875 | J34: =(J31*(1+$C$31)/($C$30-$C$31))/((1+$C$30)^J28) -> 64.032502 | K34: =(K31*(1+$C$31)/($C$30-$C$31))/((1+$C$30)^K28) -> 60.751899
E35: Enterprise Value (EV) | F35: - | G35: =G33+G34 -> 80 | H35: =H33+H34 -> 81.132324 | I35: =I33+I34 -> 82.144996 | J35: =J33+J34 -> 83.161658 | K35: =K33+K34 -> 84.070842
E36: Debt /PV Debt | F36: -34.5 | G36: =$F$36/(1+$C$30)^G$28 -> -31.797235 | H36: =$F$36/(1+$C$30)^H$28 -> -29.306207 | I36: =$F$36/(1+$C$30)^I$28 -> -27.010329 | J36: =$F$36/(1+$C$30)^J$28 -> -24.894313 | K36: =$F$36/(1+$C$30)^K$28 -> -22.944067
E37: Equtity Value | G37: =G35+G36 -> 48.202765 | H37: =H35+H36 -> 51.826117 | I37: =I35+I36 -> 55.134667 | J37: =J35+J36 -> 58.267345 | K37: =K35+K36 -> 61.126775
E38: Stock Price | G38: =G37/$C$32 -> 96.213104 | H38: =H37/$C$32 -> 103.44534 | I38: =I37/$C$32 -> 110.04923 | J38: =J37/$C$32 -> 116.30209 | K38: =K37/$C$32 -> 122.00953
B40: Current market price (EUR) | C40: 68
B41: Base 2026 upside / (downside) | C41: =IFERROR(G25/C40-1,"") -> -0.02111589

Sheet DCF by Region
B2: EU
B4: EU scenario | E4: Discount Period | G4: 1 | H4: 2 | I4: 3 | J4: 4 | K4: 5
F5: Base Year | G5: 2026 | H5: 2027 | I5: 2028 | J5: 2029 | K5: 2030
B6: WACC | C6: 0.085
B7: Growth | C7: 0.01 | E7: FCF (B€) | F7: 1.9 | G7: 1.94 | H7: 1.98 | I7: 2.02 | J7: 2.06 | K7: 2.1
B8: Number of Stocks (Billions) | C8: 0.501 | E8: PV (FCF) | F8: - | G8: =G7/(1+$C$6)^G4 -> 1.7880184 | H8: =H7/(1+$C$6)^H4 -> 1.6819215 | I8: =I7/(1+$C$6)^I4 -> 1.5814744 | J8: =J7/(1+$C$6)^J4 -> 1.486443 | K8: =K7/(1+$C$6)^K4 -> 1.3965954
E9: Sum of PV FCF (FY25-29) | G9: =SUM(D8:G8) -> 1.7880184 | H9: =SUM(D8:H8) -> 3.4699399 | I9: =SUM(E8:I8) -> 5.0514143 | J9: =SUM(F8:J8) -> 6.5378573 | K9: =SUM(G8:K8) -> 7.9344527
E10: Terminal Value (TV) | F10: - | G10: =(G7*(1+$C$7)/($C$6-$C$7))/((1+$C$6)^G4) -> 24.078648 | H10: =(H7*(1+$C$7)/($C$6-$C$7))/(1+$C$6)^H4 -> 22.649876 | I10: =(I7*(1+$C$7)/($C$6-$C$7))/(1+$C$6)^I4 -> 21.297188 | J10: =(J7*(1+$C$7)/($C$6-$C$7))/(1+$C$6)^J4 -> 20.017433 | K10: =((K7*(1+$C$7))/($C$6-$C$7))/(1+$C$6)^K4 -> 18.807485
E11: Enterprise Value (EV) | F11: - | G11: =G9+G10 -> 25.866667 | H11: =H9+H10 -> 26.119816 | I11: =I9+I10 -> 26.348602 | J11: =J9+J10 -> 26.55529 | K11: =K9+K10 -> 26.741937
B14: China
B16: China scenario | E16: Discount Period | G16: 1 | H16: 2 | I16: 3 | J16: 4 | K16: 5
F17: Base Year | G17: 2026 | H17: 2027 | I17: 2028 | J17: 2029 | K17: 2030
B18: WACC | C18: 0.115
B19: Growth | C19: 0 | E19: FCF (B€) | F19: 0.75 | G19: 0.76 | H19: 0.77 | I19: 0.78 | J19: 0.79 | K19: 0.8
B20: Number of Stocks (Billions) | C20: 0.501 | E20: PV (FCF) | F20: - | G20: =G19/(1+$C$18)^G$16 -> 0.68161435 | H20: =H19/(1+$C$18)^H$16 -> 0.61935691 | I20: =I19/(1+$C$18)^I$16 -> 0.56269104 | J20: =J19/(1+$C$18)^J$16 -> 0.51112559 | K20: =K19/(1+$C$18)^K$16 -> 0.46421124
E21: Sum of PV FCF (FY25-29) | G21: =SUM(D20:G20) -> 0.68161435 | H21: =SUM(D20:H20) -> 1.3009713 | I21: =SUM(E20:I20) -> 1.8636623 | J21: =SUM(F20:J20) -> 2.3747879 | K21: =SUM(G20:K20) -> 2.8389991
E22: Terminal Value (TV) | F22: - | G22: =(G19*(1+$C$19)/($C$18-$C$19))/(1+$C$18)^G$16 -> 5.9270813 | H22: =(H19*(1+$C$19)/($C$18-$C$19))/(1+$C$18)^H$16 -> 5.3857123 | I22: =(I19*(1+$C$19)/($C$18-$C$19))/(1+$C$18)^I$16 -> 4.8929656 | J22: =(J19*(1+$C$19)/($C$18-$C$19))/(1+$C$18)^J$16 -> 4.4445703 | K22: =(K19*(1+$C$19)/($C$18-$C$19))/(1+$C$18)^K$16 -> 4.0366195
E23: Enterprise Value (EV) | F23: - | G23: =G21+G22 -> 6.6086957 | H23: =H21+H22 -> 6.6866836 | I23: =I21+I22 -> 6.7566279 | J23: =J21+J22 -> 6.8193582 | K23: =K21+K22 -> 6.8756186
B25: NAR
B27: NAR scenario | E27: Discount Period | G27: 1 | H27: 2 | I27: 3 | J27: 4 | K27: 5
F28: Base Year | G28: 2026 | H28: 2027 | I28: 2028 | J28: 2029 | K28: 2030
B29: WACC | C29: 0.09
B30: Growth | C30: 0.015 | E30: FCF (B€) | F30: 1.35 | G30: 1.39 | H30: 1.43 | I30: 1.47 | J30: 1.51 | K30: 1.56
B31: Number of Stocks (Billions) | C31: 0.501 | E31: PV (FCF) | F31: - | G31: =G30/(1+$C$29)^G$27 -> 1.2752294 | H31: =H30/(1+$C$29)^H$27 -> 1.2036024 | I31: =I30/(1+$C$29)^I$27 -> 1.1351097 | J31: =J30/(1+$C$29)^J$27 -> 1.0697221 | K31: =K30/(1+$C$29)^K$27 -> 1.013893
E32: Sum of PV FCF (FY25-29) | G32: =SUM(D31:G31) -> 1.2752294 | H32: =SUM(D31:H31) -> 2.4788317 | I32: =SUM(E31:I31) -> 3.6139415 | J32: =SUM(F31:J31) -> 4.6836635 | K32: =SUM(G31:K31) -> 5.6975565
E33: Terminal Value (TV) | F33: - | G33: =(G30*(1+$C$30)/($C$29-$C$30))/(1+$C$29)^G$27 -> 17.258104 | H33: =(H30*(1+$C$30)/($C$29-$C$30))/(1+$C$29)^H$27 -> 16.288752 | I33: =(I30*(1+$C$30)/($C$29-$C$30))/(1+$C$29)^I$27 -> 15.361818 | J33: =(J30*(1+$C$30)/($C$29-$C$30))/(1+$C$29)^J$27 -> 14.476905 | K33: =(K30*(1+$C$30)/($C$29-$C$30))/(1+$C$29)^K$27 -> 13.721351
E34: Enterprise Value (EV) | F34: - | G34: =G32+G33 -> 18.533333 | H34: =H32+H33 -> 18.767584 | I34: =I32+I33 -> 18.97576 | J34: =J32+J33 -> 19.160569 | K34: =K32+K33 -> 19.418908
B37: Other regions
B39: Other regions scenario | E39: Discount Period | G39: 1 | H39: 2 | I39: 3 | J39: 4 | K39: 5
F40: Base Year | G40: 2026 | H40: 2027 | I40: 2028 | J40: 2029 | K40: 2030
B41: WACC | C41: 0.1
B42: Growth | C42: 0.01 | E42: FCF (B€) | F42: 0.65 | G42: 0.66 | H42: 0.67 | I42: 0.68 | J42: 0.69 | K42: 0.7
B43: Number of Stocks (Billions) | C43: 0.501 | E43: PV (FCF) | F43: - | G43: =G42/(1+$C$41)^G$39 -> 0.6 | H43: =H42/(1+$C$41)^H$39 -> 0.55371901 | I43: =I42/(1+$C$41)^I$39 -> 0.51089406 | J43: =J42/(1+$C$41)^J$39 -> 0.47127928 | K43: =K42/(1+$C$41)^K$39 -> 0.43464493
E44: Sum of PV FCF (FY25-29) | G44: =SUM(D43:G43) -> 0.6 | H44: =SUM(D43:H43) -> 1.153719 | I44: =SUM(E43:I43) -> 1.6646131 | J44: =SUM(F43:J43) -> 2.1358924 | K44: =SUM(G43:K43) -> 2.5705373
E45: Terminal Value (TV) | F45: - | G45: =(G42*(1+$C$42)/($C$41-$C$42))/(1+$C$41)^G$39 -> 6.7333333 | H45: =(H42*(1+$C$42)/($C$41-$C$42))/(1+$C$41)^H$39 -> 6.2139578 | I45: =(I42*(1+$C$42)/($C$41-$C$42))/(1+$C$41)^I$39 -> 5.7333667 | J45: =(J42*(1+$C$42)/($C$41-$C$42))/(1+$C$41)^J$39 -> 5.2888009 | K45: =(K42*(1+$C$42)/($C$41-$C$42))/(1+$C$41)^K$39 -> 4.8776819
E46: Enterprise Value (EV) | F46: - | G46: =G44+G45 -> 7.3333333 | H46: =H44+H45 -> 7.3676768 | I46: =I44+I45 -> 7.3979798 | J46: =J44+J45 -> 7.4246932 | K46: =K44+K45 -> 7.4482192

Sheet Update Log
A1: Valuation Recalibration - 21 Oct 2026
A3: Reference | B3: Value
A4: Current market price (EUR) | B4: 68
A6: Method | B6: 2026 value / share | C6: Upside / (downside) | D6: Key assumption
A7: SOTP | B7: ='SOTP Valuation'!D34 -> 67.858683 | C7: =IFERROR(B7/$B$4-1,"") -> -0.0020781965 | D7: 2.3x normalized Automotive FCF plus China and Finance
A8: DCF by Business | B8: ='DCF by Business'!G13 -> 67.736774 | C8: =IFERROR(B8/$B$4-1,"") -> -0.0038709683 | D8: 9.0% WACC, 1.0% terminal growth, EUR 34.5bn debt
A9: DCF Bear | B9: ='DCF Scenarios'!G12 -> 49.837838 | C9: =IFERROR(B9/$B$4-1,"") -> -0.26709062 | D9: 10.5% WACC, 0.0% terminal growth
A10: DCF Base | B10: ='DCF Scenarios'!G25 -> 66.564119 | C10: =IFERROR(B10/$B$4-1,"") -> -0.02111589 | D10: 9.0% WACC, 1.0% terminal growth
A11: DCF Bull | B11: ='DCF Scenarios'!G38 -> 96.213104 | C11: =IFERROR(B11/$B$4-1,"") -> 0.41489858 | D11: 8.5% WACC, 1.5% terminal growth
A13: The EUR 68 market price is a reasonableness anchor, not a forced valuation target.
